{
  "apertix_plus_dmt": {
    "combination": "Apertix (Adjoint Corridor) + dmt",
    "composite_type": "⟨𐑦 · 𐑸 · 𐑾 · 𐑬 · 𐑐 · 𐑧 · 𐑲 · 𐑵 · ⊙ · 𐑫 · 𐑳 · 𐑭⟩",
    "composite_tier": "O_2",
    "parent_1": {
      "name": "Apertix (Adjoint Corridor)",
      "tier": "O_2"
    },
    "parent_2": {
      "name": "dmt",
      "tier": "O_inf"
    },
    "deltas_from_parent_1": [
      {
        "primitive": "T",
        "from": "𐑥",
        "to": "𐑸",
        "delta": 2
      },
      {
        "primitive": "R",
        "from": "𐑽",
        "to": "𐑾",
        "delta": 1
      },
      {
        "primitive": "Gm",
        "from": "𐑠",
        "to": "𐑵",
        "delta": 1
      },
      {
        "primitive": "H",
        "from": "𐑖",
        "to": "𐑫",
        "delta": 1
      },
      {
        "primitive": "W",
        "from": "𐑴",
        "to": "𐑭",
        "delta": 1
      }
    ],
    "deltas_from_parent_2": [
      {
        "primitive": "P",
        "from": "𐑹",
        "to": "𐑬",
        "delta": -2
      }
    ],
    "key_changes": [],
    "synergy_prediction": "low synergy — composite is structurally distant from both parents",
    "warning": "No special warnings — standard psychedelic safety protocols apply."
  },
  "apertix_plus_psilocybin": {
    "combination": "Apertix (Adjoint Corridor) + psilocybin",
    "composite_type": "⟨𐑦 · 𐑥 · 𐑾 · 𐑬 · 𐑐 · 𐑧 · 𐑲 · 𐑠 · ⊙ · 𐑖 · 𐑳 · 𐑭⟩",
    "composite_tier": "O_2",
    "parent_1": {
      "name": "Apertix (Adjoint Corridor)",
      "tier": "O_2"
    },
    "parent_2": {
      "name": "psilocybin",
      "tier": "O_2"
    },
    "deltas_from_parent_1": [
      {
        "primitive": "R",
        "from": "𐑽",
        "to": "𐑾",
        "delta": 1
      },
      {
        "primitive": "W",
        "from": "𐑴",
        "to": "𐑭",
        "delta": 1
      }
    ],
    "deltas_from_parent_2": [
      {
        "primitive": "D",
        "from": "𐑼",
        "to": "𐑦",
        "delta": 1
      }
    ],
    "key_changes": [],
    "synergy_prediction": "moderate synergy",
    "warning": "No special warnings — standard psychedelic safety protocols apply."
  },
  "apertix_plus_lsd": {
    "combination": "Apertix (Adjoint Corridor) + lsd",
    "composite_type": "⟨𐑦 · 𐑸 · 𐑾 · 𐑬 · 𐑐 · 𐑧 · 𐑲 · 𐑵 · ⊙ · 𐑖 · 𐑳 · 𐑭⟩",
    "composite_tier": "O_2",
    "parent_1": {
      "name": "Apertix (Adjoint Corridor)",
      "tier": "O_2"
    },
    "parent_2": {
      "name": "lsd",
      "tier": "O_inf"
    },
    "deltas_from_parent_1": [
      {
        "primitive": "T",
        "from": "𐑥",
        "to": "𐑸",
        "delta": 2
      },
      {
        "primitive": "R",
        "from": "𐑽",
        "to": "𐑾",
        "delta": 1
      },
      {
        "primitive": "Gm",
        "from": "𐑠",
        "to": "𐑵",
        "delta": 1
      },
      {
        "primitive": "W",
        "from": "𐑴",
        "to": "𐑭",
        "delta": 1
      }
    ],
    "deltas_from_parent_2": [
      {
        "primitive": "P",
        "from": "𐑹",
        "to": "𐑬",
        "delta": -2
      }
    ],
    "key_changes": [],
    "synergy_prediction": "low synergy — composite is structurally distant from both parents",
    "warning": "No special warnings — standard psychedelic safety protocols apply."
  },
  "apertix_plus_ketamine": {
    "combination": "Apertix (Adjoint Corridor) + ketamine",
    "composite_type": "⟨𐑦 · 𐑥 · 𐑾 · 𐑿 · 𐑱 · 𐑧 · 𐑲 · 𐑠 · ⊙ · 𐑖 · 𐑳 · 𐑴⟩",
    "composite_tier": "O_1",
    "parent_1": {
      "name": "Apertix (Adjoint Corridor)",
      "tier": "O_2"
    },
    "parent_2": {
      "name": "ketamine",
      "tier": "O_1"
    },
    "deltas_from_parent_1": [
      {
        "primitive": "R",
        "from": "𐑽",
        "to": "𐑾",
        "delta": 1
      },
      {
        "primitive": "P",
        "from": "𐑬",
        "to": "𐑿",
        "delta": -1
      },
      {
        "primitive": "F",
        "from": "𐑐",
        "to": "𐑱",
        "delta": -2
      }
    ],
    "deltas_from_parent_2": [
      {
        "primitive": "D",
        "from": "𐑼",
        "to": "𐑦",
        "delta": 1
      },
      {
        "primitive": "K",
        "from": "𐑤",
        "to": "𐑧",
        "delta": 1
      },
      {
        "primitive": "G",
        "from": "𐑔",
        "to": "𐑲",
        "delta": 1
      },
      {
        "primitive": "Ph",
        "from": "𐑢",
        "to": "⊙",
        "delta": 1
      },
      {
        "primitive": "H",
        "from": "𐑒",
        "to": "𐑖",
        "delta": 1
      },
      {
        "primitive": "S",
        "from": "𐑕",
        "to": "𐑳",
        "delta": 1
      },
      {
        "primitive": "W",
        "from": "𐑷",
        "to": "𐑴",
        "delta": 1
      }
    ],
    "key_changes": [],
    "synergy_prediction": "low synergy — composite is structurally distant from both parents",
    "warning": "No special warnings — standard psychedelic safety protocols apply."
  },
  "apertix_plus_mdma": {
    "combination": "Apertix (Adjoint Corridor) + mdma",
    "composite_type": "⟨𐑦 · 𐑥 · 𐑾 · 𐑿 · 𐑞 · 𐑧 · 𐑲 · 𐑠 · 𐑮 · 𐑖 · 𐑳 · 𐑴⟩",
    "composite_tier": "O_1",
    "parent_1": {
      "name": "Apertix (Adjoint Corridor)",
      "tier": "O_2"
    },
    "parent_2": {
      "name": "mdma",
      "tier": "O_1"
    },
    "deltas_from_parent_1": [
      {
        "primitive": "R",
        "from": "𐑽",
        "to": "𐑾",
        "delta": 1
      },
      {
        "primitive": "P",
        "from": "𐑬",
        "to": "𐑿",
        "delta": -1
      },
      {
        "primitive": "F",
        "from": "𐑐",
        "to": "𐑞",
        "delta": -1
      },
      {
        "primitive": "Ph",
        "from": "⊙",
        "to": "𐑮",
        "delta": 0.33000000000000007
      }
    ],
    "deltas_from_parent_2": [
      {
        "primitive": "D",
        "from": "𐑼",
        "to": "𐑦",
        "delta": 1
      },
      {
        "primitive": "T",
        "from": "𐑡",
        "to": "𐑥",
        "delta": 2
      },
      {
        "primitive": "K",
        "from": "𐑤",
        "to": "𐑧",
        "delta": 1
      },
      {
        "primitive": "H",
        "from": "𐑒",
        "to": "𐑖",
        "delta": 1
      },
      {
        "primitive": "W",
        "from": "𐑷",
        "to": "𐑴",
        "delta": 1
      }
    ],
    "key_changes": [],
    "synergy_prediction": "low synergy — composite is structurally distant from both parents",
    "warning": "No special warnings — standard psychedelic safety protocols apply."
  },
  "apertix_plus_mescaline": {
    "combination": "Apertix (Adjoint Corridor) + mescaline",
    "composite_type": "⟨𐑦 · 𐑥 · 𐑽 · 𐑗 · 𐑱 · 𐑧 · 𐑲 · 𐑠 · ⊙ · 𐑖 · 𐑳 · 𐑴⟩",
    "composite_tier": "O_1",
    "parent_1": {
      "name": "Apertix (Adjoint Corridor)",
      "tier": "O_2"
    },
    "parent_2": {
      "name": "mescaline",
      "tier": "O_0"
    },
    "deltas_from_parent_1": [
      {
        "primitive": "P",
        "from": "𐑬",
        "to": "𐑗",
        "delta": -2
      },
      {
        "primitive": "F",
        "from": "𐑐",
        "to": "𐑱",
        "delta": -2
      }
    ],
    "deltas_from_parent_2": [
      {
        "primitive": "D",
        "from": "𐑼",
        "to": "𐑦",
        "delta": 1
      },
      {
        "primitive": "T",
        "from": "𐑡",
        "to": "𐑥",
        "delta": 2
      },
      {
        "primitive": "R",
        "from": "𐑩",
        "to": "𐑽",
        "delta": 2
      },
      {
        "primitive": "G",
        "from": "𐑔",
        "to": "𐑲",
        "delta": 1
      },
      {
        "primitive": "Gm",
        "from": "𐑜",
        "to": "𐑠",
        "delta": 1
      },
      {
        "primitive": "Ph",
        "from": "𐑢",
        "to": "⊙",
        "delta": 1
      },
      {
        "primitive": "H",
        "from": "𐑒",
        "to": "𐑖",
        "delta": 1
      },
      {
        "primitive": "S",
        "from": "𐑙",
        "to": "𐑳",
        "delta": 2
      },
      {
        "primitive": "W",
        "from": "𐑷",
        "to": "𐑴",
        "delta": 1
      }
    ],
    "key_changes": [],
    "synergy_prediction": "low synergy — composite is structurally distant from both parents",
    "warning": "No special warnings — standard psychedelic safety protocols apply."
  },
  "apertix_plus_verticullum": {
    "combination": "Apertix (Adjoint Corridor) + Verticullum (EP-Lever)",
    "composite_type": "⟨𐑦 · 𐑥 · 𐑾 · 𐑬 · 𐑐 · 𐑧 · 𐑲 · 𐑠 · ⊙ · 𐑫 · 𐑳 · 𐑟⟩",
    "composite_tier": "O_2",
    "parent_1": {
      "name": "Apertix (Adjoint Corridor)",
      "tier": "O_2"
    },
    "parent_2": {
      "name": "Verticullum (EP-Lever)",
      "tier": "O_inf"
    },
    "deltas_from_parent_1": [
      {
        "primitive": "R",
        "from": "𐑽",
        "to": "𐑾",
        "delta": 1
      },
      {
        "primitive": "H",
        "from": "𐑖",
        "to": "𐑫",
        "delta": 1
      },
      {
        "primitive": "W",
        "from": "𐑴",
        "to": "𐑟",
        "delta": 2
      }
    ],
    "deltas_from_parent_2": [
      {
        "primitive": "P",
        "from": "𐑹",
        "to": "𐑬",
        "delta": -2
      }
    ],
    "key_changes": [],
    "synergy_prediction": "low synergy — composite is structurally distant from both parents",
    "warning": "Non-Abelian winding from combination — topological complexity extreme"
  },
  "apertix_plus_chimerium": {
    "combination": "Apertix (Adjoint Corridor) + Chimerium (Supercritical Catalyst)",
    "composite_type": "⟨𐑦 · 𐑸 · 𐑾 · 𐑬 · 𐑐 · 𐑧 · 𐑲 · 𐑵 · 𐑣 · 𐑫 · 𐑳 · 𐑭⟩",
    "composite_tier": "O_0",
    "parent_1": {
      "name": "Apertix (Adjoint Corridor)",
      "tier": "O_2"
    },
    "parent_2": {
      "name": "Chimerium (Supercritical Catalyst)",
      "tier": "O_0"
    },
    "deltas_from_parent_1": [
      {
        "primitive": "T",
        "from": "𐑥",
        "to": "𐑸",
        "delta": 2
      },
      {
        "primitive": "R",
        "from": "𐑽",
        "to": "𐑾",
        "delta": 1
      },
      {
        "primitive": "Gm",
        "from": "𐑠",
        "to": "𐑵",
        "delta": 1
      },
      {
        "primitive": "Ph",
        "from": "⊙",
        "to": "𐑣",
        "delta": 1
      },
      {
        "primitive": "H",
        "from": "𐑖",
        "to": "𐑫",
        "delta": 1
      },
      {
        "primitive": "W",
        "from": "𐑴",
        "to": "𐑭",
        "delta": 1
      }
    ],
    "deltas_from_parent_2": [
      {
        "primitive": "P",
        "from": "𐑹",
        "to": "𐑬",
        "delta": -2
      }
    ],
    "key_changes": [],
    "synergy_prediction": "low synergy — composite is structurally distant from both parents",
    "warning": "SUPERCRITICAL: combination may trigger runaway effects"
  },
  "apertix_plus_retiarius": {
    "combination": "Apertix (Adjoint Corridor) + Retiarius (Local-Net Trap)",
    "composite_type": "⟨𐑦 · 𐑥 · 𐑾 · 𐑿 · 𐑞 · 𐑺 · 𐑲 · 𐑠 · 𐑮 · 𐑖 · 𐑳 · 𐑴⟩",
    "composite_tier": "O_1",
    "parent_1": {
      "name": "Apertix (Adjoint Corridor)",
      "tier": "O_2"
    },
    "parent_2": {
      "name": "Retiarius (Local-Net Trap)",
      "tier": "O_1"
    },
    "deltas_from_parent_1": [
      {
        "primitive": "R",
        "from": "𐑽",
        "to": "𐑾",
        "delta": 1
      },
      {
        "primitive": "P",
        "from": "𐑬",
        "to": "𐑿",
        "delta": -1
      },
      {
        "primitive": "F",
        "from": "𐑐",
        "to": "𐑞",
        "delta": -1
      },
      {
        "primitive": "K",
        "from": "𐑧",
        "to": "𐑺",
        "delta": 1.5
      },
      {
        "primitive": "Ph",
        "from": "⊙",
        "to": "𐑮",
        "delta": 0.33000000000000007
      }
    ],
    "deltas_from_parent_2": [
      {
        "primitive": "D",
        "from": "𐑼",
        "to": "𐑦",
        "delta": 1
      },
      {
        "primitive": "T",
        "from": "𐑡",
        "to": "𐑥",
        "delta": 2
      },
      {
        "primitive": "G",
        "from": "𐑚",
        "to": "𐑲",
        "delta": 2
      },
      {
        "primitive": "Gm",
        "from": "𐑜",
        "to": "𐑠",
        "delta": 1
      },
      {
        "primitive": "H",
        "from": "𐑒",
        "to": "𐑖",
        "delta": 1
      },
      {
        "primitive": "S",
        "from": "𐑕",
        "to": "𐑳",
        "delta": 1
      },
      {
        "primitive": "W",
        "from": "𐑷",
        "to": "𐑴",
        "delta": 1
      }
    ],
    "key_changes": [],
    "synergy_prediction": "low synergy — composite is structurally distant from both parents",
    "warning": "No special warnings — standard psychedelic safety protocols apply."
  },
  "apertix_plus_praxeum": {
    "combination": "Apertix (Adjoint Corridor) + Praxeum (EP-Core Control Platform)",
    "composite_type": "⟨𐑦 · 𐑶 · 𐑾 · 𐑬 · 𐑐 · 𐑧 · 𐑲 · 𐑠 · 𐑻 · 𐑫 · 𐑳 · 𐑭⟩",
    "composite_tier": "O_0",
    "parent_1": {
      "name": "Apertix (Adjoint Corridor)",
      "tier": "O_2"
    },
    "parent_2": {
      "name": "Praxeum (EP-Core Control Platform)",
      "tier": "O_0"
    },
    "deltas_from_parent_1": [
      {
        "primitive": "T",
        "from": "𐑥",
        "to": "𐑶",
        "delta": 1
      },
      {
        "primitive": "R",
        "from": "𐑽",
        "to": "𐑾",
        "delta": 1
      },
      {
        "primitive": "Ph",
        "from": "⊙",
        "to": "𐑻",
        "delta": 0.6699999999999999
      },
      {
        "primitive": "H",
        "from": "𐑖",
        "to": "𐑫",
        "delta": 1
      },
      {
        "primitive": "W",
        "from": "𐑴",
        "to": "𐑭",
        "delta": 1
      }
    ],
    "deltas_from_parent_2": [
      {
        "primitive": "P",
        "from": "𐑹",
        "to": "𐑬",
        "delta": -2
      }
    ],
    "key_changes": [],
    "synergy_prediction": "low synergy — composite is structurally distant from both parents",
    "warning": "EP ABSORPTION: Gate 1 (self-modeling) may close uncontrollably"
  }
}