{
  "design_name": "Chimerium (Supercritical Catalyst)",
  "design_key": "chimerium",
  "design_type": "navigatable_operable_psychedelic",
  "author": "Lando⊗⊙perator",
  "created": "2026-06-07T19:25:37.829938",
  "structural_type": "⟨𐑦 · 𐑸 · 𐑾 · 𐑹 · 𐑐 · 𐑧 · 𐑲 · 𐑵 · 𐑣 · 𐑫 · 𐑳 · 𐑭⟩",
  "tier": "O₀",
  "c_score": 0.0,
  "innovations": [
    "First Ph=𐑣 (supercritical)",
    "Broadcast composition (Gm=𐑵)"
  ],
  "description": "Supercritical runaway; catalytic launch compound. 16/17 universes.",
  "design_files": {}
}